{"V9NpswBt1UWRlo/xaqplzw==":"imgres-2000x1498.jpg","6bO/zGEf6xspx902NfICSg==":"images-2000x1120.jpg","QMKewVDlwwvAe1OsyLJMUQ==":"images-2000x1498.jpg","II/hGdbcwpaF2R+B7nCpqw==":"gorgeous-man-cave-room-2400x1350-wallpaper-2000x1125.jpg","+otLk+tSNsApnGKDgcdCdA==":"6206d9e86f7fc33b4bd5edbb755010da-2000x1125.jpg","cBWcMt140ra/yJz9UrI8Wg==":"-1x-2000x1125.jpg","L6AK8luWxmusp9ZVDaqclg==":"stylized-to-ir-man-as-wells-as-finding-man-cave-ideas-home-design-ideas_man-cave-ideas-2000x1332.jpg","auPKh0ikO03ptLlGO1kn/w==":"images-118x128.png","SFprWeDAsODYUqZnxSqkzQ==":"interior-billiards-room-billiard-room-table-pool-balls-cues-furniture-bulbs-sports-holiday-600x400.jpg","/g/uQp2EueibyWUO+CRChw==":"theme-theaters-jets-600x450.jpg","3+nq350jQ+B9DQoqI60EYw==":"room-projector-sony-lspx-interior-a-movie-transformers-600x375.jpg","UJfN5Nv+/jYEDauk5PwG3w==":"unknown-600x336.png","R6+Iolf2x9vwfZwJIxhgIg==":"unknown-2000x1051.png","uGYmMV0K8BTX430zAMmHYA==":"unknown-2000x1360.png","h1DRVpfCDtK3aQ98emzTHQ==":"unknown-2000x1230.png","U/91Ke3E1IP61zMHeXnueg==":"unknown-2000x680.png","OW5bU8z/9JYBmC6qj1/RJg==":"unknown-2000x1120.png","PoMgYoWsS2B5xA3QLdcU9Q==":"unknown-2000x2285.png","hYvD5zMyytAofp9IMKXiQQ==":"unknown-600x315.png","PBmNpuGUqVV2SUo2d8vS8Q==":"unknown-600x408.png","0De5zK7RzlkGqs0Llbp27A==":"unknown-600x369.png","nqgrxcknSuau3QPSNSrSXA==":"unknown-600x204.png","31Mzj1udX/ZlNVbQStMSLQ==":"unknown-1-600x336.png","PQpxefJ2UKPJWKwyWsM03Q==":"unknown-600x685.png","qcKWzUmwOZnAtfTBzxdS/g==":"baseball%201-600x336.jpg","4LJ3fKmYMdc4HneYj0oYNw==":"baseball%202-600x400.jpg","ojijiNC3VI8AJnBFBZSQ8A==":"baseball%203-600x398.jpg","vLThcElnFF+qHpOefyTYsQ==":"baseball%204-600x397.jpg","I7kg/ottiEJtUkMzr1PrdQ==":"baseball%205-600x399.jpg","SBK0TLvNABQbUoMLro9YlA==":"sport%201-600x417.jpg","/C5bJfhE3jNs8REinjjTxg==":"sports%203-600x449.jpg","CuIVlGiLw+JFcfGla9127w==":"sports%203-1400x1048.jpg"}